stingray/__init__.py
stingray/cobol_parser.py
stingray/estruct.py
stingray/implementations.py
stingray/schema_instance.py
stingray/workbook.py
stingray_reader-5.1.1.dist-info/METADATA
stingray_reader-5.1.1.dist-info/WHEEL
stingray_reader-5.1.1.dist-info/licenses/LICENSE
stingray_reader-5.1.1.dist-info/RECORD
