Metadata-Version: 2.3
Name: stingray-reader
Version: 5.1.1
Summary: The Stingray Schema-Based File Reader
Project-URL: Homepage, https://slott56.github.io/Stingray-Reader/build/html/index.html
Project-URL: GitHub, https://github.com/slott56/Stingray-Reader
Author-email: "S.Lott" <slott56@gmail.com>
License: MIT License
License-File: LICENSE
Classifier: Development Status :: 6 - Mature
Classifier: Environment :: Console
Classifier: Intended Audience :: Developers
Classifier: Operating System :: OS Independent
Classifier: Programming Language :: Python
Requires-Python: >=3.12
Requires-Dist: jsonschema>=4.23.0
Requires-Dist: numbers-parser>=4.13.2
Requires-Dist: openpyxl>=3.1.5
Requires-Dist: pyexcel[ods]>=0.7.0
Requires-Dist: xlrd>=2.0.1
